{
  "required": true,
  "package": "cc.thonly.polydex2rei.mixin",
  "plugin": "cc.thonly.polydex2rei.Polydex2REIMixinPlugin",
  "compatibilityLevel": "JAVA_21",
  "mixins": [
    "ExampleMixin",
    "RoughlyEnoughItemsNetworkMixin",
    "ServerDisplayRegistryImplMixin",
    "ViewSearchBuilderImplMixin"
  ],
  "injectors": {
    "defaultRequire": 1
  },
  "overwrites": {
    "requireAnnotations": true
  },
  "client": [
    "ReiCompatibilityMixin",
    "AbstractDisplayViewingScreenMixin",
    "ClientHelperImplMixin",
    "CompositeDisplayViewingScreenMixin",
    "DefaultDisplayViewingScreenMixin",
    "DisplayedEntryWidgetMixin",
    "EntryWidgetMixin",
    "ItemEntryDefinitionMixin",
    "ScreenOverlayImplMixin"
  ]
}